hdrbg/__init__.py
hdrbg-0.1.2.dist-info/METADATA
hdrbg-0.1.2.dist-info/WHEEL
hdrbg-0.1.2.dist-info/licenses/LICENSE
hdrbg-0.1.2.dist-info/RECORD
