Metadata-Version: 2.4
Name: hdrbg
Version: 0.1.2
Summary: NIST SP800-90A hash DRBG
Project-URL: Homepage, https://github.com/sebastien-riou/hash-drbg
Project-URL: Bug Tracker, https://github.com/sebastien-riou/hash-drbg/issues
Author: Sebastien Riou
License-File: LICENSE
Classifier: Development Status :: 4 - Beta
Classifier: License :: OSI Approved :: Apache Software License
Classifier: Operating System :: OS Independent
Classifier: Programming Language :: Python :: 3.10
Classifier: Programming Language :: Python :: 3.11
Classifier: Programming Language :: Python :: 3.12
Classifier: Programming Language :: Python :: Implementation :: CPython
Classifier: Programming Language :: Python :: Implementation :: PyPy
Requires-Python: >=3.10
Requires-Dist: pysatl>=1.2.6
Provides-Extra: doc
Requires-Dist: sphinx; extra == 'doc'
